RippleCarryAdder/RCA.v
// Arquitectura de computadores, Sección 10
// Giovanni Jimenez 22469
// -------------- RIPPLE CARRY ADDER -------------


module FullAdder(
    input A, B, Cin,
    output Sum, Cout
);
    assign Sum = A ^ B ^ Cin;
    assign Cout = (A & B) | (Cin & (A ^ B));
endmodule


module RippleCarryAdder16 (
    input  [15:0] A,
    input  [15:0] B,
    input        Cin,
    output [31:0] Sum   // Salida de 32 bits como lo piden
);
    wire [15:0] sum_internal;
    wire [15:0] carry;

    // Primer bit
    FullAdder FA0 (
        .A(A[0]), .B(B[0]), .Cin(Cin),
        .Sum(sum_internal[0]), .Cout(carry[0])
    );

    // Bits 1 a 15
    genvar i;
    generate
        for (i = 1; i < 16; i = i + 1) begin : ripple
            FullAdder FA (
                .A(A[i]), .B(B[i]), .Cin(carry[i-1]),
                .Sum(sum_internal[i]), .Cout(carry[i])
            );
        end
    endgenerate

    // Salida de 32 bits: bits [15:0] = sum, bit [16] = último carry, bits [31:17] = 0
    assign Sum = {15'b0, carry[15], sum_internal};

endmodule


/*
module FullAdder(
    input A, B, Cin,
    output Sum, Cout
);
    wire sum1, c1, c2;

    assign sum1 = A ^ B;
    assign Sum = sum1 ^ Cin;

    assign c1 = A & B;
    assign c2 = sum1 & Cin;
    assign Cout = c1 | c2;

    xor (sum1, A, B);
    xor (Sum, sum1, Cin);

    and (c1, A, B);
    and (c2, sum1, Cin);
    or  (Cout, c1, c2);
endmodule
*/

`timescale 1fs / 1fs

module testbench;
    // ================================================
    // 1. DECLARACIÓN DE SEÑALES
    // ================================================
    // Señales para conectar al DUT (Design Under Test)
    reg [15:0] A;         // Señal de 16 bits (controlada desde el testbench)
    reg [15:0] B;         // Señal de 16 bits (controlada desde el testbench)
    reg Cin;              // Señal del carry in (controlada por el testbench)
    wire [31:0] Sum;      // Salida del sumador (monitoreada por el testbench)

    time start_time, end_time;  // Variables para medir el tiempo

    // ================================================
    // 2. INSTANCIACIÓN DEL DISEÑO BAJO PRUEBA (DUT)
    // ================================================
    // Conectamos las señales del testbench al módulo sumador
    RippleCarryAdder16 dut (
        .A(A),    // Conecta señal A del testbench a A del sumador
        .B(B),    // Conecta señal B del testbench a B del sumador
        .Cin(Cin),    // Conecta señal Cin del testbench a Cin del sumador
        .Sum(Sum)    // Conecta señal Sum del testbench a Sum del sumador

    );
    // ================================================
    // 3. GENERACIÓN DE ESTÍMULOS Y MONITOREO
    // ================================================
    initial begin
        // Sistema de monitoreo: muestra señales en consola cuando cambian
        //$monitor("Tiempo=%0t | A=%b | B=%b | Cin=%b | Sum=%b | Cout=%b", $time, A, B, Cin, Sum, Cout);
        
        // --------------------------
        // Secuencia de pruebas:
        // --------------------------
        
         $display("===== RCA16 Test Cases =====");

        // CASO 1: Suma de ceros
        A = 0; B = 0; Cin = 0;
        start_time = $time; #1; end_time = $time;
        $display("Caso 1: A=%b, B=%b Cin=%b -> Sum=%b, delta_t=%0t", A, B, Cin, Sum, end_time - start_time);

        // CASO 2: Uno más uno
        A = 1; B = 1; Cin = 0;
        start_time = $time; #1; end_time = $time;
        $display("Caso 2: A=%b, B=%b Cin=%b -> Sum=%b,  delta_t=%0t", A, B, Cin, Sum, end_time - start_time);

        // CASO 3: Overflow máximo
        A = 16'hFFFF; B = 1; Cin = 0;
        start_time = $time; #1; end_time = $time;
        $display("Caso 3: A=%b, B=%b Cin=%b -> Sum=%b, delta_t=%0t", A, B, Cin, Sum, end_time - start_time);

        // CASO 4: Suma sin carry
        A = 10; B = 5; Cin = 0;
        start_time = $time; #1; end_time = $time;
        $display("Caso 4: A=%b, B=%b Cin=%b -> Sum=%b, delta_t=%0t", A, B, Cin, Sum, end_time - start_time);

        // CASO 5: Carry propagado largo
        A = 32767; B = 1; Cin = 0;
        start_time = $time; #1; end_time = $time;
        $display("Caso 5: A=%b, B=%b Cin=%b -> Sum=%b, delta_t=%0t", A, B, Cin, Sum, end_time - start_time);

        // CASO 6: Mitades altas
        A = 61440; B = 3855; Cin = 0;
        start_time = $time; #1; end_time = $time;
        $display("Caso 6: A=%b, B=%b Cin=%b -> Sum=%b, delta_t=%0t", A, B, Cin, Sum, end_time - start_time);

        // CASO 7: Aleatorios pequeños
        A = 5; B = 3; Cin = 0;
        start_time = $time; #1; end_time = $time;
        $display("Caso 7: A=%b, B=%b Cin=%b -> Sum=%b, delta_t=%0t", A, B, Cin, Sum, end_time - start_time);

        // CASO 8: Aleatorios grandes
        A = 43690; B = 21845; Cin = 0;
        start_time = $time; #1; end_time = $time;
        $display("Caso 8: A=%b, B=%b Cin=%b -> Sum=%b, delta_t=%0t", A, B, Cin, Sum, end_time - start_time);

        // CASO 9: Cero en un operando
        A = 0; B = 21845; Cin = 0;
        start_time = $time; #1; end_time = $time;
        $display("Caso 9: A=%b, B=%b Cin=%b -> Sum=%b, delta_t=%0t", A, B, Cin, Sum, end_time - start_time);

        // CASO 10: Overflow doble
        A = 16'hFFFF; B = 16'hFFFF; Cin = 0;
        start_time = $time; #1; end_time = $time;
        $display("Caso 10: A=%b, B=%b Cin=%b -> Sum=%b, delta_t=%0t", A, B, Cin, Sum, end_time - start_time);


        // Finaliza la simulación
        $finish;  
    end

    initial begin
        $dumpfile("RCA.vcd");  // 1. Especifica el nombre del archivo de salida
        $dumpvars(0, testbench);    // 2. Define qué señales guardar y en qué jerarquía
    end

endmodule

RippleCarryAdder/RCA.vcd
$date
	Mon Sep 01 22:46:38 2025
$end
$version
	Icarus Verilog
$end
$timescale
	1fs
$end
$scope module testbench $end
$var wire 32 ! Sum [31:0] $end
$var reg 16 " A [15:0] $end
$var reg 16 # B [15:0] $end
$var reg 1 $ Cin $end
$var reg 64 % end_time [63:0] $end
$var reg 64 & start_time [63:0] $end
$scope module dut $end
$var wire 16 ' A [15:0] $end
$var wire 16 ( B [15:0] $end
$var wire 1 $ Cin $end
$var wire 16 ) sum_internal [15:0] $end
$var wire 16 * carry [15:0] $end
$var wire 32 + Sum [31:0] $end
$scope begin ripple[1] $end
$var parameter 2 , i $end
$scope module FA $end
$var wire 1 - A $end
$var wire 1 . B $end
$var wire 1 / Cin $end
$var wire 1 0 Cout $end
$var wire 1 1 Sum $end
$upscope $end
$upscope $end
$scope begin ripple[2] $end
$var parameter 3 2 i $end
$scope module FA $end
$var wire 1 3 A $end
$var wire 1 4 B $end
$var wire 1 5 Cin $end
$var wire 1 6 Cout $end
$var wire 1 7 Sum $end
$upscope $end
$upscope $end
$scope begin ripple[3] $end
$var parameter 3 8 i $end
$scope module FA $end
$var wire 1 9 A $end
$var wire 1 : B $end
$var wire 1 ; Cin $end
$var wire 1 < Cout $end
$var wire 1 = Sum $end
$upscope $end
$upscope $end
$scope begin ripple[4] $end
$var parameter 4 > i $end
$scope module FA $end
$var wire 1 ? A $end
$var wire 1 @ B $end
$var wire 1 A Cin $end
$var wire 1 B Cout $end
$var wire 1 C Sum $end
$upscope $end
$upscope $end
$scope begin ripple[5] $end
$var parameter 4 D i $end
$scope module FA $end
$var wire 1 E A $end
$var wire 1 F B $end
$var wire 1 G Cin $end
$var wire 1 H Cout $end
$var wire 1 I Sum $end
$upscope $end
$upscope $end
$scope begin ripple[6] $end
$var parameter 4 J i $end
$scope module FA $end
$var wire 1 K A $end
$var wire 1 L B $end
$var wire 1 M Cin $end
$var wire 1 N Cout $end
$var wire 1 O Sum $end
$upscope $end
$upscope $end
$scope begin ripple[7] $end
$var parameter 4 P i $end
$scope module FA $end
$var wire 1 Q A $end
$var wire 1 R B $end
$var wire 1 S Cin $end
$var wire 1 T Cout $end
$var wire 1 U Sum $end
$upscope $end
$upscope $end
$scope begin ripple[8] $end
$var parameter 5 V i $end
$scope module FA $end
$var wire 1 W A $end
$var wire 1 X B $end
$var wire 1 Y Cin $end
$var wire 1 Z Cout $end
$var wire 1 [ Sum $end
$upscope $end
$upscope $end
$scope begin ripple[9] $end
$var parameter 5 \ i $end
$scope module FA $end
$var wire 1 ] A $end
$var wire 1 ^ B $end
$var wire 1 _ Cin $end
$var wire 1 ` Cout $end
$var wire 1 a Sum $end
$upscope $end
$upscope $end
$scope begin ripple[10] $end
$var parameter 5 b i $end
$scope module FA $end
$var wire 1 c A $end
$var wire 1 d B $end
$var wire 1 e Cin $end
$var wire 1 f Cout $end
$var wire 1 g Sum $end
$upscope $end
$upscope $end
$scope begin ripple[11] $end
$var parameter 5 h i $end
$scope module FA $end
$var wire 1 i A $end
$var wire 1 j B $end
$var wire 1 k Cin $end
$var wire 1 l Cout $end
$var wire 1 m Sum $end
$upscope $end
$upscope $end
$scope begin ripple[12] $end
$var parameter 5 n i $end
$scope module FA $end
$var wire 1 o A $end
$var wire 1 p B $end
$var wire 1 q Cin $end
$var wire 1 r Cout $end
$var wire 1 s Sum $end
$upscope $end
$upscope $end
$scope begin ripple[13] $end
$var parameter 5 t i $end
$scope module FA $end
$var wire 1 u A $end
$var wire 1 v B $end
$var wire 1 w Cin $end
$var wire 1 x Cout $end
$var wire 1 y Sum $end
$upscope $end
$upscope $end
$scope begin ripple[14] $end
$var parameter 5 z i $end
$scope module FA $end
$var wire 1 { A $end
$var wire 1 | B $end
$var wire 1 } Cin $end
$var wire 1 ~ Cout $end
$var wire 1 !" Sum $end
$upscope $end
$upscope $end
$scope begin ripple[15] $end
$var parameter 5 "" i $end
$scope module FA $end
$var wire 1 #" A $end
$var wire 1 $" B $end
$var wire 1 %" Cin $end
$var wire 1 &" Cout $end
$var wire 1 '" Sum $end
$upscope $end
$upscope $end
$scope module FA0 $end
$var wire 1 (" A $end
$var wire 1 )" B $end
$var wire 1 $ Cin $end
$var wire 1 *" Cout $end
$var wire 1 +" Sum $end
$upscope $end
$upscope $end
$upscope $end
$enddefinitions $end
$comment Show the parameter values. $end
$dumpall
b1111 ""
b1110 z
b1101 t
b1100 n
b1011 h
b1010 b
b1001 \
b1000 V
b111 P
b110 J
b101 D
b100 >
b11 8
b10 2
b1 ,
$end
#0
$dumpvars
0+"
0*"
0)"
0("
0'"
0&"
0%"
0$"
0#"
0!"
0~
0}
0|
0{
0y
0x
0w
0v
0u
0s
0r
0q
0p
0o
0m
0l
0k
0j
0i
0g
0f
0e
0d
0c
0a
0`
0_
0^
0]
0[
0Z
0Y
0X
0W
0U
0T
0S
0R
0Q
0O
0N
0M
0L
0K
0I
0H
0G
0F
0E
0C
0B
0A
0@
0?
0=
0<
0;
0:
09
07
06
05
04
03
01
00
0/
0.
0-
b0 +
b0 *
b0 )
b0 (
b0 '
b0 &
bx %
0$
b0 #
b0 "
b0 !
$end
#1
b10 !
b10 +
b10 )
11
1/
b1 *
1*"
1)"
1("
b1 &
b1 #
b1 (
b1 "
b1 '
b1 %
#2
1&"
1%"
1~
1}
1x
1w
1r
1q
1l
1k
1f
1e
1`
1_
1Z
1Y
1T
1S
1N
1M
1H
1G
1B
1A
1<
1;
16
15
b1111111111111111 *
10
01
07
0=
0C
0I
0O
0U
0[
0a
0g
0m
0s
0y
0!"
b10000000000000000 !
b10000000000000000 +
b0 )
0'"
1-
13
19
1?
1E
1K
1Q
1W
1]
1c
1i
1o
1u
1{
1#"
b10 &
b1111111111111111 "
b1111111111111111 '
b10 %
#3
0A
0<
1=
0;
06
17
05
00
0G
0M
0S
0Y
0_
0e
0k
0q
0w
0}
0%"
11
0B
0H
0N
0T
0Z
0`
0f
0l
0r
0x
0~
0&"
0/
0C
0I
0O
0U
0[
0a
0g
0m
0s
0y
0!"
0'"
b1111 !
b1111 +
b1111 )
1+"
b0 *
0*"
14
03
0?
0E
0K
0Q
0W
0]
0c
0i
0o
0u
0{
0#"
0("
b11 &
b101 #
b101 (
b1010 "
b1010 '
b11 %
#4
1'"
1%"
1~
1}
1x
1w
1r
1q
1l
1k
1f
1e
1`
1_
1Z
1Y
1T
1S
1N
1M
1H
1G
1B
1A
1<
0=
1;
16
07
15
10
01
1/
0C
0I
0O
0U
0[
0a
0g
0m
0s
0y
0!"
b1000000000000000 !
b1000000000000000 +
b1000000000000000 )
0+"
b111111111111111 *
1*"
04
13
1?
1E
1K
1Q
1W
1]
1c
1i
1o
1u
1{
1("
b100 &
b1 #
b1 (
b111111111111111 "
b111111111111111 '
b100 %
#5
0%"
0~
1!"
0}
0x
1y
0w
0r
1s
0q
0l
1m
0k
0f
0A
1g
0<
0e
1=
0`
0;
1a
06
0_
17
0Z
05
1[
00
0G
0M
0S
0Y
11
0B
0H
0N
0T
0&"
0/
0C
0I
0O
0U
1'"
b1111111100001111 !
b1111111100001111 +
b1111111100001111 )
1+"
b0 *
0*"
1.
14
1:
1X
1^
1d
1j
0-
03
09
0?
0E
0K
0Q
0W
0]
0c
0i
1#"
0("
b101 &
b111100001111 #
b111100001111 (
b1111000000000000 "
b1111000000000000 '
b101 %
#6
1;
16
07
15
10
01
1/
1=
0[
0a
0g
0m
0s
0y
0!"
0'"
b1000 !
b1000 +
b1000 )
0+"
b111 *
1*"
04
0:
0X
0^
0d
0j
13
0o
0u
0{
0#"
1("
b110 &
b11 #
b11 (
b101 "
b101 '
b110 %
#7
0&"
0%"
0~
0}
0x
0w
0r
0q
0l
0k
0f
0e
0`
0_
0Z
0Y
0T
0S
0N
0M
0H
0;
06
0G
17
0B
05
00
0A
11
0<
0/
1C
1O
1[
1g
1s
1!"
1=
1I
1U
1a
1m
1y
1'"
b1111111111111111 !
b1111111111111111 +
b1111111111111111 )
1+"
b0 *
0*"
0.
14
1@
1L
1X
1d
1p
1|
1-
03
19
1E
1Q
1]
1i
1u
1#"
0("
b111 &
b101010101010101 #
b101010101010101 (
b1010101010101010 "
b1010101010101010 '
b111 %
#8
01
0=
0I
0U
0a
0m
0y
b101010101010101 !
b101010101010101 +
b101010101010101 )
0'"
0-
09
0E
0Q
0]
0i
0u
0#"
b1000 &
b0 "
b0 '
b1000 %
#9
1=
1I
1U
1a
1m
1y
1'"
11
15
1;
1A
1G
1M
1S
1Y
1_
1e
1k
1q
1w
1}
1%"
1/
10
17
16
1<
1C
1B
1H
1O
1N
1T
1[
1Z
1`
1g
1f
1l
1s
1r
1x
1!"
1~
1&"
b11111111111111110 !
b11111111111111110 +
b1111111111111110 )
0+"
b1111111111111111 *
1*"
1.
1:
1F
1R
1^
1j
1v
1$"
1-
13
19
1?
1E
1K
1Q
1W
1]
1c
1i
1o
1u
1{
1#"
1("
b1001 &
b1111111111111111 #
b1111111111111111 (
b1111111111111111 "
b1111111111111111 '
b1001 %
#10
b1010 %
