Contador4bits.v
module contador (
    input clk,
    input reset,
    output reg [3:0] count
);
    always @(posedge clk or posedge reset)
    begin
        if (reset)
            count <= 4'b0000;
        else
            count <= count + 1;
    end
endmodule

module testbench;
    // ================================================
    // 1. DECLARACIÓN DE SEÑALES
    // ================================================
    // Señales para conectar al DUT (Design Under Test)
    reg clk;         // Reloj (señal periódica generada por el testbench)
    reg reset;       // Señal de reset (controlada por el testbench)
    wire [3:0] count; // Salida del contador (monitoreada por el testbench)

    // ================================================
    // 2. INSTANCIACIÓN DEL DISEÑO BAJO PRUEBA (DUT)
    // ================================================
    // Conectamos las señales del testbench al módulo contador
    contador dut (
        .clk(clk),    // Conecta señal clk del testbench a clk del contador
        .reset(reset), // Conecta señal reset del testbench a reset del contador
        .count(count) // Conecta salida count del contador a señal del testbench
    );

    // ================================================
    // 3. GENERACIÓN DE RELOJ (CLOCK)
    // ================================================
    initial begin
        clk = 0;  // Inicializa el reloj en 0
        // Bucle infinito: conmuta el reloj cada 5 unidades de tiempo
        forever #5 clk = ~clk;  // Período = 10 unidades (5 alto + 5 bajo)
    end

    // ================================================
    // 4. GENERACIÓN DE ESTÍMULOS Y MONITOREO
    // ================================================
    initial begin
        // Sistema de monitoreo: muestra señales en consola cuando cambian
        $monitor("Tiempo=%0t | clk=%b | reset=%b | count=%d (%b)", 
                 $time, clk, reset, count, count);
        
        // --------------------------
        // Secuencia de pruebas:
        // --------------------------
        
        // Caso 1: Reset inicial
        reset = 1;  // Activa reset (pone contador en cero)
        #10;        // Espera 10 unidades de tiempo (1 ciclo completo de reloj)
        
        // Caso 2: Conteo normal
        reset = 0;  // Desactiva reset (contador empieza a contar)
        #50;        // Espera 50 unidades (5 ciclos completos de reloj)
        
        // Caso 3: Reset durante operación
        reset = 1;  // Vuelve a activar reset (detiene conteo)
        #10;        // Espera 10 unidades (1 ciclo)
        
        // Caso 4: Reanudar conteo
        reset = 0;  // Desactiva reset nuevamente
        #30;        // Espera 30 unidades (3 ciclos)

        // Finaliza la simulación
        $finish;  
    end

    initial begin
        $dumpfile("contador.vcd");  // 1. Especifica el nombre del archivo de salida
        $dumpvars(0, testbench);    // 2. Define qué señales guardar y en qué jerarquía
    end

endmodule

contador.vcd
$date
	Mon Aug 18 15:20:09 2025
$end
$version
	Icarus Verilog
$end
$timescale
	1s
$end
$scope module testbench $end
$var wire 4 ! count [3:0] $end
$var reg 1 " clk $end
$var reg 1 # reset $end
$scope module dut $end
$var wire 1 " clk $end
$var wire 1 # reset $end
$var reg 4 $ count [3:0] $end
$upscope $end
$upscope $end
$enddefinitions $end
$comment Show the parameter values. $end
$dumpall
$end
#0
$dumpvars
b0 $
1#
0"
b0 !
$end
#5
1"
#10
0"
0#
#15
b1 !
b1 $
1"
#20
0"
#25
b10 !
b10 $
1"
#30
0"
#35
b11 !
b11 $
1"
#40
0"
#45
b100 !
b100 $
1"
#50
0"
#55
b101 !
b101 $
1"
#60
b0 !
b0 $
0"
1#
#65
1"
#70
0"
0#
#75
b1 !
b1 $
1"
#80
0"
#85
b10 !
b10 $
1"
#90
0"
#95
b11 !
b11 $
1"
