Proyecto/IMEM&PC/IMEM+PC.v
// ================================================
//  Universidad del Valle de Guatemala
//  Arquitectura de computadores, sección 10
//  Giovanni Jimenez 22469
//  Ever Yes 22510
//  IMEM + PROGRAM COUNTER
// ================================================


`timescale 1ns/1ps
// ===================================================
//  Módulo: PC (Program Counter)
// ===================================================
module PC (
    input  wire        clk,
    input  wire        reset,          // reset asíncrono
    input  wire [31:0] next_pc,
    output reg  [31:0] current_pc
);
    always @(posedge clk or posedge reset) begin
        if (reset)
            current_pc <= 32'd0;
        else
            current_pc <= next_pc;
    end
endmodule

// ===================================================
//  Módulo: IMEM de 16 WORDS
//  Dirección en bytes → índice de palabra = addr[5:2]
// ===================================================
module IMEM (
    input  wire [31:0] addr,
    output wire [31:0] instruction
);
    reg [31:0] memory [0:15];

    // Instrucciones de ejemplo
    initial begin
        // 0: ADD  $3, $1, $2
        memory[0] = 32'b000000_00001_00010_00011_00000_100000;
        // 1: ADDI $9, $8, 10
        memory[1] = 32'b001000_01000_01001_0000000000001010;
        // 2: AND  $5, $3, $4
        memory[2] = 32'b000000_00011_00100_00101_00000_100100;
        // 3: OR   $6, $3, $4
        memory[3] = 32'b000000_00011_00100_00110_00000_100101;
        // 4: SLT  $7, $1, $2
        memory[4] = 32'b000000_00001_00010_00111_00000_101010;
        // 5: LW   $10, 4($9)
        memory[5] = 32'b100011_01001_01010_0000000000000100;
        // 6: SW   $10, 8($9)
        memory[6] = 32'b101011_01001_01010_0000000000001000;
        // 7: BEQ  $1, $2, 3
        memory[7] = 32'b000100_00001_00010_0000000000000011;
        // 8: ADDI $8, $0, 255
        memory[8] = 32'b001000_00000_01000_0000000011111111;
        // 9: ORI  $11, $8, 0x00AA
        memory[9] = 32'b001101_01000_01011_0000000010101010;

        memory[10] = 32'h00000000;
        memory[11] = 32'h00000000;
        memory[12] = 32'h00000000;
        memory[13] = 32'h00000000;
        memory[14] = 32'h00000000;
        memory[15] = 32'h00000000;
    end

    // 16 palabras → índice 0..15 desde addr en bytes
    assign instruction = memory[addr[5:2]];
endmodule


// ===================================================
//  Testbench: Integración PC + IMEM
// ===================================================
module testbench;
    // ================================================
    // 1) DECLARACIÓN DE SEÑALES
    // ================================================
    reg         clk;
    reg         reset;
    reg  [31:0] next_pc;
    wire [31:0] current_pc;
    wire [31:0] instruction;

    // Campos para decodificación
    reg  [5:0]  opcode;
    reg  [4:0]  rs, rt, rd, shamt;
    reg  [5:0]  funct;
    reg  [15:0] imm;

    integer ciclo;

    // Parámetro: paso del PC (4 bytes por instrucción)
    localparam STEP = 32'd4;

    // ================================================
    // 2) INSTANCIACIÓN DE DUTs (PC + IMEM)
    // ================================================
    PC   u_pc   (.clk(clk), .reset(reset), .next_pc(next_pc), .current_pc(current_pc));
    IMEM u_imem (.addr(current_pc), .instruction(instruction));

    // ================================================
    // 3) ESTÍMULOS, RELOJ Y MONITOREO
    // ================================================
    // Reloj 100 MHz
    initial clk = 1'b0;
    always #5 clk = ~clk;

    // Contador de ciclos
    initial ciclo = 0;
    always @(posedge clk) ciclo <= ciclo + 1;

    // Avance automático del PC: cambiar next_pc lejos del posedge
    always @(negedge clk) begin
        if (reset)
            next_pc <= 32'd0;
        else
            next_pc <= current_pc + STEP;
    end

    // Decodificación + impresión cada ciclo (después del posedge)
    always @(posedge clk) begin
        // Extraer campos
        opcode = instruction[31:26];
        rs     = instruction[25:21];
        rt     = instruction[20:16];
        rd     = instruction[15:11];
        shamt  = instruction[10:6];
        funct  = instruction[5:0];
        imm    = instruction[15:0];

        // Línea 1: PC e instrucción partida con guiones bajos
        $write("PC=%0d, Instr=", current_pc);
        $write("%06b_", instruction[31:26]); // opcode
        $write("%05b_", instruction[25:21]); // rs
        $write("%05b_", instruction[20:16]); // rt
        $write("%05b_", instruction[15:11]); // rd
        $write("%05b_", instruction[10:6]);  // shamt
        $write("%06b\n", instruction[5:0]);  // funct / parte baja

        // Línea 2: campos ya interpretados
        if (opcode == 6'b000000) begin
            $display("opcode=%06b rs=%05b rt=%05b rd=%05b shamt=%05b funct=%06b",
                     opcode, rs, rt, rd, shamt, funct);
        end else begin
            $display("opcode=%06b rs=%05b rt=%05b immediate=%016b (signed=%0d)",
                     opcode, rs, rt, imm, $signed(imm));
        end
        $display("---");
    end

    // Secuencia de reset y fin
    initial begin
        // VCD
        $dumpfile("PC_IMEM.vcd");
        $dumpvars(0, testbench);

        // Reset
        reset   = 1'b1;
        next_pc = 32'd0;
        repeat (2) @(posedge clk);
        reset = 1'b0;

        // Correr ~12 ciclos (suficiente para ver las 10 instrucciones)
        repeat (12) @(posedge clk);

        $finish;
    end
endmodule

Proyecto/IMEM&PC/PC_IMEM.vcd
$date
	Sun Oct 12 21:10:28 2025
$end
$version
	Icarus Verilog
$end
$timescale
	1ps
$end
$scope module testbench $end
$var wire 32 ! instruction [31:0] $end
$var wire 32 " current_pc [31:0] $end
$var parameter 32 # STEP $end
$var reg 1 $ clk $end
$var reg 6 % funct [5:0] $end
$var reg 16 & imm [15:0] $end
$var reg 32 ' next_pc [31:0] $end
$var reg 6 ( opcode [5:0] $end
$var reg 5 ) rd [4:0] $end
$var reg 1 * reset $end
$var reg 5 + rs [4:0] $end
$var reg 5 , rt [4:0] $end
$var reg 5 - shamt [4:0] $end
$var integer 32 . ciclo [31:0] $end
$scope module u_imem $end
$var wire 32 / instruction [31:0] $end
$var wire 32 0 addr [31:0] $end
$upscope $end
$scope module u_pc $end
$var wire 1 $ clk $end
$var wire 32 1 next_pc [31:0] $end
$var wire 1 * reset $end
$var reg 32 2 current_pc [31:0] $end
$upscope $end
$upscope $end
$enddefinitions $end
$comment Show the parameter values. $end
$dumpall
b100 #
$end
#0
$dumpvars
b0 2
b0 1
b0 0
b1000100001100000100000 /
b0 .
bx -
bx ,
bx +
1*
bx )
bx (
b0 '
bx &
bx %
0$
b0 "
b1000100001100000100000 !
$end
#5000
b1 .
b1100000100000 &
b100000 %
b0 -
b11 )
b10 ,
b1 +
b0 (
1$
#10000
0$
#15000
b10 .
0*
1$
#20000
b100 '
b100 1
0$
#25000
b100001000010010000000000001010 !
b100001000010010000000000001010 /
b100 "
b100 0
b100 2
b11 .
1$
#30000
b1000 '
b1000 1
0$
#35000
b11001000010100000100100 !
b11001000010100000100100 /
b1000 "
b1000 0
b1000 2
b100 .
b1010 &
b1010 %
b0 )
b1001 ,
b1000 +
b1000 (
1$
#40000
b1100 '
b1100 1
0$
#45000
b11001000011000000100101 !
b11001000011000000100101 /
b1100 "
b1100 0
b1100 2
b101 .
b10100000100100 &
b100100 %
b101 )
b100 ,
b11 +
b0 (
1$
#50000
b10000 '
b10000 1
0$
#55000
b1000100011100000101010 !
b1000100011100000101010 /
b10000 "
b10000 0
b10000 2
b110 .
b11000000100101 &
b100101 %
b110 )
1$
#60000
b10100 '
b10100 1
0$
#65000
b10001101001010100000000000000100 !
b10001101001010100000000000000100 /
b10100 "
b10100 0
b10100 2
b111 .
b11100000101010 &
b101010 %
b111 )
b10 ,
b1 +
1$
#70000
b11000 '
b11000 1
0$
#75000
b10101101001010100000000000001000 !
b10101101001010100000000000001000 /
b11000 "
b11000 0
b11000 2
b1000 .
b100 &
b100 %
b0 )
b1010 ,
b1001 +
b100011 (
1$
#80000
b11100 '
b11100 1
0$
#85000
b10000001000100000000000000011 !
b10000001000100000000000000011 /
b11100 "
b11100 0
b11100 2
b1001 .
b1000 &
b1000 %
b101011 (
1$
#90000
b100000 '
b100000 1
0$
#95000
b100000000010000000000011111111 !
b100000000010000000000011111111 /
b100000 "
b100000 0
b100000 2
b1010 .
b11 &
b11 %
b10 ,
b1 +
b100 (
1$
#100000
b100100 '
b100100 1
0$
#105000
b110101000010110000000010101010 !
b110101000010110000000010101010 /
b100100 "
b100100 0
b100100 2
b1011 .
b11111111 &
b111111 %
b11 -
b1000 ,
b0 +
b1000 (
1$
#110000
b101000 '
b101000 1
0$
#115000
b0 !
b0 /
b101000 "
b101000 0
b101000 2
b1100 .
b10101010 &
b101010 %
b10 -
b1011 ,
b1000 +
b1101 (
1$
#120000
b101100 '
b101100 1
0$
#125000
b101100 "
b101100 0
b101100 2
b1101 .
b0 &
b0 %
b0 -
b0 ,
b0 +
b0 (
1$
#130000
b110000 '
b110000 1
0$
#135000
b110000 "
b110000 0
b110000 2
b1110 .
1$
