Ej4_CounterWithEnable/CounterE.v
// Arquitectura de computadores, Sección 10
// Giovanni Jimenez 22469

module contadorE (
    input clk,
    input reset,
    input enable,
    output reg [2:0] count
);
    always @(posedge clk or posedge reset or posedge enable)
    begin
        if (reset)
            count <= 3'b000;
        else if (enable)
            count <= count + 1; 
    end
endmodule


module testbench;
    // ================================================
    // 1. DECLARACIÓN DE SEÑALES
    // ================================================
    // Señales para conectar al DUT (Design Under Test)
    reg clk;         // Reloj (señal periódica generada por el testbench)
    reg reset;       // Señal de reset (controlada por el testbench)
    reg enable;      // Señal del enable (controlada por el testbench)
    wire [2:0] count; // Salida del contador (monitoreada por el testbench)

    // ================================================
    // 2. INSTANCIACIÓN DEL DISEÑO BAJO PRUEBA (DUT)
    // ================================================
    // Conectamos las señales del testbench al módulo contador
    contadorE dut (
        .clk(clk),    // Conecta señal clk del testbench a clk del contador
        .reset(reset), // Conecta señal reset del testbench a reset del contador
        .enable(enable), // Conecta señal reset del testbench a reset del contador
        .count(count) // Conecta salida count del contador a señal del testbench
    );

    // ================================================
    // 3. GENERACIÓN DE RELOJ (CLOCK)
    // ================================================
    initial begin
        clk = 0;  // Inicializa el reloj en 0
        // Bucle infinito: conmuta el reloj cada 5 unidades de tiempo
        forever #5 clk = ~clk;  // Período = 10 unidades (5 alto + 5 bajo)
    end

    // ================================================
    // 4. GENERACIÓN DE ESTÍMULOS Y MONITOREO
    // ================================================
    initial begin
        // Sistema de monitoreo: muestra señales en consola cuando cambian
        $monitor("Tiempo=%0t | clk=%b | reset=%b | enable=%b | count=%d", 
                 $time, clk, reset, count, count);
        
        // --------------------------
        // Secuencia de pruebas:
        // --------------------------
        
        // Paso 1: Reset inicial
        reset = 1;  // Activa reset (pone contador en cero)
        enable = 0;  // establece inicialmente el enable en 0
        #10;        // Espera 10 unidades de tiempo (1 ciclo completo de reloj)
        
        // Paso 2: Conteo normal
        reset = 0;  // Desactiva reset (contador empieza a contar)
        enable = 1;  // Permite el conteo
        #20;        // Espera 50 unidades (5 ciclos completos de reloj)

        // Paso 3: Reset durante conteo
        reset = 1;  //  Activa el reset (se reincia el conteo)
        enable = 1;  // Permite el conteo
        #10;        // Espera 50 unidades (5 ciclos completos de reloj)

        // Paso 4: se desactiva el reset, para permitir el conteo
        reset = 0;  // Desactiva reset
        #20         // Espera 50 unidades (5 ciclos completos de reloj)
        
        // Paso 5: Para el conteo debido a enable = 0
        reset = 0;  // Conteo normal, reset desactivado
        enable = 0;  // desactiva el enable, bloquea el conteo
        #10;        // Espera 10 unidades (1 ciclo)
        
        // Paso 6: Reanudar conteo
        reset = 0;  // Desactiva reset nuevamente
        enable = 1;  // Activa el enable, permite el conteo
        #30;        // Espera 30 unidades (3 ciclos)

        // Finaliza la simulación
        $finish;  
    end

    initial begin
        $dumpfile("contadorE.vcd");  // 1. Especifica el nombre del archivo de salida
        $dumpvars(0, testbench);    // 2. Define qué señales guardar y en qué jerarquía
    end

endmodule

Ej4_CounterWithEnable/contadorE.vcd
$date
	Thu Aug 21 18:19:36 2025
$end
$version
	Icarus Verilog
$end
$timescale
	1s
$end
$scope module testbench $end
$var wire 3 ! count [2:0] $end
$var reg 1 " clk $end
$var reg 1 # enable $end
$var reg 1 $ reset $end
$scope module dut $end
$var wire 1 " clk $end
$var wire 1 # enable $end
$var wire 1 $ reset $end
$var reg 3 % count [2:0] $end
$upscope $end
$upscope $end
$enddefinitions $end
$comment Show the parameter values. $end
$dumpall
$end
#0
$dumpvars
b0 %
1$
0#
0"
b0 !
$end
#5
1"
#10
b1 !
b1 %
0"
1#
0$
#15
b10 !
b10 %
1"
#20
0"
#25
b11 !
b11 %
1"
#30
b0 !
b0 %
0"
1$
#35
1"
#40
0"
0$
#45
b1 !
b1 %
1"
#50
0"
#55
b10 !
b10 %
1"
#60
0"
0#
#65
1"
#70
b11 !
b11 %
0"
1#
#75
b100 !
b100 %
1"
#80
0"
#85
b101 !
b101 %
1"
#90
0"
#95
b110 !
b110 %
1"
